.gitignore
README.md
setup.py
cryptotoolbox/.gitignore
cryptotoolbox/__init__.py
cryptotoolbox.egg-info/PKG-INFO
cryptotoolbox.egg-info/SOURCES.txt
cryptotoolbox.egg-info/dependency_links.txt
cryptotoolbox.egg-info/top_level.txt
cryptotoolbox/analyzer/__init__.py
cryptotoolbox/analyzer/hourly_market.py
cryptotoolbox/analyzer/market.py
cryptotoolbox/analyzer/minutely_market.py
cryptotoolbox/backtest/__init__.py
cryptotoolbox/backtest/dynamic_plot_backtest.py
cryptotoolbox/backtest/plot_backtest.py
cryptotoolbox/backtest/plot_tools.py
cryptotoolbox/backtest/print_stats.py
cryptotoolbox/binanceutils/__init__.py
cryptotoolbox/binanceutils/binanceutils.py
cryptotoolbox/boosted_trees/__init__.py
cryptotoolbox/boosted_trees/roll_lightgbm.py
cryptotoolbox/bot/__init__.py
cryptotoolbox/bot/binance_bot.py
cryptotoolbox/bot/binance_spot_bot.py
cryptotoolbox/callback/__init__.py
cryptotoolbox/callback/ts_callback.py
cryptotoolbox/cointegration_utils/cointegration_parameters_generator.py
cryptotoolbox/cointegration_utils/cointegration_runner.py
cryptotoolbox/cointegration_utils/cointegration_signal_generator.py
cryptotoolbox/cointegration_utils/cointegration_utilities.py
cryptotoolbox/cointegration_utils/cointegration_utils_numpy/signal_generator.py
cryptotoolbox/cointegration_utils/cointegration_utils_numpy/utilities.py
cryptotoolbox/colab/__init__.py
cryptotoolbox/colab/colab_utility.py
cryptotoolbox/comparison_kpis/__init__.py
cryptotoolbox/comparison_kpis/comparison_plot_utility.py
cryptotoolbox/config/__init__.py
cryptotoolbox/config/loader/__init__.py
cryptotoolbox/config/loader/abstractreader.py
cryptotoolbox/config/loader/reader.py
cryptotoolbox/config/object/__init__.py
cryptotoolbox/config/object/config.py
cryptotoolbox/config/object/environment.py
cryptotoolbox/config/object/model_param_cointegration.py
cryptotoolbox/config/object/modelparamtemplate.py
cryptotoolbox/config/object/profile.py
cryptotoolbox/config/parser/__init__.py
cryptotoolbox/config/parser/abstractparser.py
cryptotoolbox/config/parser/parsertemplate.py
cryptotoolbox/connector/__init__.py
cryptotoolbox/connector/augmento_connector.py
