Metadata-Version: 1.1
Name: cryptotoolbox
Version: 0.6.24
Summary: Dashboard for financial market data
Home-page: UNKNOWN
Author: stefan duprey
Author-email: stefan.duprey@gmail.com
License: MIT
Download-URL: https://github.com/sduprey/cryptotoolbox/archive/6.0.0.tar.gz
Platform: UNKNOWN
Classifier: Development Status :: 4 - Beta
Classifier: Intended Audience :: Financial and Insurance Industry
Classifier: Intended Audience :: Science/Research
Classifier: License :: OSI Approved :: MIT License
Classifier: Operating System :: POSIX :: Linux
Classifier: Programming Language :: Python :: 3.8
Classifier: Topic :: Office/Business :: Financial
Classifier: Topic :: Scientific/Engineering :: Artificial Intelligence
